{
    "Start": {
        "backtrackable": true, 
        "forceconnect": [
            false, 
            false
        ], 
        "returnchance": 0
    }, 
    "Chain": {
        "backtrackable": true, 
        "forceconnect": [
            false, 
            false
        ], 
        "returnchance": 0
    }, 
    "ChainFinal": {
        "backtrackable": true, 
        "forceconnect": [
            false, 
            false
        ], 
        "returnchance": 0
    }, 
    "ChainLinear": {
        "backtrackable": true, 
        "forceconnect": [
            false, 
            false
        ], 
        "returnchance": 0
    }, 
    "ChainParallel": {
        "backtrackable": true, 
        "forceconnect": [
            false, 
            false
        ], 
        "returnchance": 0
    }, 
    "Fork": {
        "backtrackable": true, 
        "forceconnect": [
            false, 
            false
        ], 
        "returnchance": 0
    }, 
    "Gate": {
        "backtrackable": true, 
        "forceconnect": [
            false, 
            false
        ], 
        "returnchance": 0
    }, 
    "Hook": {
        "backtrackable": true, 
        "forceconnect": [
            false, 
            false
        ], 
        "returnchance": 0
    }, 

    "ItemBonus": {
        "backtrackable": true, 
        "forceconnect": [
            false, 
            false
        ], 
        "returnchance": 0,
        "entities": {
            
        },
        "door_id": 1
    }, 
    "ItemQuest": {
        "backtrackable": false, 
        "forceconnect": [
            false, 
            false
        ], 
        "returnchance": 0,
        "entities": {
            
        },
        "door_id": 1
    }, 
    "Key": {
        "backtrackable": true, 
        "forceconnect": [
            false, 
            false
        ], 
        "returnchance": 0.6,
        "entities": {
            "animated.collectable.key": 1.0
        },
        "door_id": 1
    }, 
    "KeyFinal": {
        "backtrackable": true, 
        "forceconnect": [
            false, 
            false
        ], 
        "returnchance": 0,
        "entities": {
            
        },
        "door_id": 1
    }, 
    "KeyMulti": {
        "backtrackable": true, 
        "forceconnect": [
            false, 
            false
        ], 
        "returnchance": 0.4,
        "entities": {
            
        },
        "door_id": 1
    }, 
    "Lock": {
        "backtrackable": false, 
        "forceconnect": [
            false, 
            false
        ], 
        "returnchance": 0,
        "entities": {
            
        },
        "door_id": 1
    }, 
    "LockFinal": {
        "backtrackable": false, 
        "forceconnect": [
            false, 
            false
        ], 
        "returnchance": 0,
        "entities": {
            
        },
        "door_id": 1
    }, 
    "LockMulti": {
        "backtrackable": false, 
        "forceconnect": [
            false, 
            false
        ], 
        "returnchance": 0,
        "entities": {
            
        },
        "door_id": 1
    }, 
    "Nothing": {
        "backtrackable": true, 
        "forceconnect": [
            false, 
            false
        ], 
        "returnchance": 0,
        "entities": {
            
        },
        "door_id": 1
    }, 
    "Test": {
        "backtrackable": false, 
        "forceconnect": [
            false, 
            false
        ], 
        "returnchance": 0,
        "entities": {
            
        },
        "door_id": 1
    }, 
    "TestItem": {
        "backtrackable": false, 
        "forceconnect": [
            false, 
            false
        ], 
        "returnchance": 0,
        "entities": {
            
        },
        "door_id": 1
    }, 
    "TestSecret": {
        "backtrackable": false, 
        "forceconnect": [
            false, 
            false
        ], 
        "returnchance": 0,
        "entities": {
            
        },
        "door_id": 1
    },
    "BossLevel": {
        "backtrackable": false, 
        "forceconnect": [
            false, 
            false
        ], 
        "returnchance": 0,
        "entities": {
            
        },
        "door_id": 9
    }, 
    "BossMini": {
        "backtrackable": false, 
        "forceconnect": [
            false, 
            false
        ], 
        "returnchance": 0,
        "entities": {
            
        },
        "door_id": 3
    }, 
    "Entrance": {
        "backtrackable": false, 
        "forceconnect": [
            false, 
            false
        ], 
        "returnchance": 0,
        "entities": {
            
        },
        "door_id": 1
    }, 
    "Goal": {
        "backtrackable": false, 
        "forceconnect": [
            false, 
            false
        ], 
        "returnchance": 0,
        "entities": {
            
        },
        "door_id": 26
    }
}